Workbook

Sheet devis
A1: Event Dream
B5: Event Dream
B6: 98 Rue Jean Jaurès
B7: 94800 Villejuif
B8: (33) 06 52 36 08 49
B11: Devis
B12: Envoyée le | C12: =TODAY() -> 45547
B14: Devis pour | F14: N° de devis
B15: Nom : | F15: =INDIRECT("'information général'!B4") -> 2912
B16: telephone :
B17: adresse : | F17: Date de location
F18: 45565
B23: Description | E23: Qté | F23: Prix unitaire | G23: Prix total
F24: =IF(B24="", "", IFERROR(VLOOKUP(B24, 'liste de matériel'!A:B, 2, FALSE), "")) | G24: =IF(E24*F24=0,"",E24*F24)
F25: =IF(B25="", "", IFERROR(VLOOKUP(B25, 'liste de matériel'!A:B, 2, FALSE), "")) | G25: =IF(E25*F25=0,"",E25*F25)
F26: =IF(B26="", "", IFERROR(VLOOKUP(B26, 'liste de matériel'!A:B, 2, FALSE), "")) | G26: =IF(E26*F26=0,"",E26*F26)
F27: =IF(B27="", "", IFERROR(VLOOKUP(B27, 'liste de matériel'!A:B, 2, FALSE), "")) | G27: =IF(E27*F27=0,"",E27*F27)
F28: =IF(B28="", "", IFERROR(VLOOKUP(B28, 'liste de matériel'!A:B, 2, FALSE), "")) | G28: =IF(E28*F28=0,"",E28*F28)
F29: =IF(B29="", "", IFERROR(VLOOKUP(B29, 'liste de matériel'!A:B, 2, FALSE), "")) | G29: =IF(E29*F29=0,"",E29*F29)
F30: =IF(B30="", "", IFERROR(VLOOKUP(B30, 'liste de matériel'!A:B, 2, FALSE), "")) | G30: =IF(E30*F30=0,"",E30*F30)
F31: =IF(B31="", "", IFERROR(VLOOKUP(B31, 'liste de matériel'!A:B, 2, FALSE), "")) | G31: =IF(E31*F31=0,"",E31*F31)
F32: =IF(B32="", "", IFERROR(VLOOKUP(B32, 'liste de matériel'!A:B, 2, FALSE), "")) | G32: =IF(E32*F32=0,"",E32*F32)
F33: =IF(B33="", "", IFERROR(VLOOKUP(B33, 'liste de matériel'!A:B, 2, FALSE), "")) | G33: =IF(E33*F33=0,"",E33*F33)
F34: =IF(B34="", "", IFERROR(VLOOKUP(B34, 'liste de matériel'!A:B, 2, FALSE), "")) | G34: =IF(E34*F34=0,"",E34*F34)
F35: =IF(B35="", "", IFERROR(VLOOKUP(B35, 'liste de matériel'!A:B, 2, FALSE), "")) | G35: =IF(E35*F35=0,"",E35*F35)
... F37: =IF(B37="", "", IFERROR(VLOOKUP(B37, 'liste de matériel'!A:B, 2, FALSE), "")) | G37: =IF(E37*F37=0,"",E37*F37)
F38: Sous-total H.T | G38: =SUM(G24:G37)-G39 -> 0
B39: Remarques : | F39: TVA | G39: =SUM(G24:G37)*0.2 -> 0
F40: =SUM(G38,G39) -> 0

Sheet information général
B3: Numéro de devis | C3: date | D3: nom prénom | E3: date de location | F3: retour de location | G3: adresse de livraison | H3: Caution | I3: Reste dû | J3: Acompte | K3: somme total
B4: =B5+1 -> 2912 | C4: =devis!C12 -> 45547 | E4: 45565 | F4: =E4+2 -> 45567 | G4: =devis!C17 | I4: =K4-J4 -> 0 | K4: =devis!F40 -> 0
B5: =B6+1 -> 2911 | C5: =devis!C10 | D5: TESTE 1 | G5: =devis!C17 | I5: =K5-J5 -> 0 | K5: =devis!F40 -> 0
B6: =B7+1 -> 2910 | C6: =devis!C11 | D6: TESTE 2 | E6: =devis!F19 | F6: =E6+2 -> 2 | G6: =devis!C17 | I6: =K6-J6 -> 0 | K6: =devis!F40 -> 0
B7: =B8+1 -> 2909 | C7: =devis!C12 -> 45547 | D7: TESTE 3 | E7: 45565 | F7: =E7+2 -> 45567 | G7: =devis!C17 | I7: =K7-J7 -> 0 | K7: =devis!F40 -> 0
B8: =B9+1 -> 2908 | C8: =devis!C12 -> 45547 | D8: HANANE
B9: 2907 | C9: 45497 | D9: nafea said | E9: 45591 | F9: 45593 | G9: 7 rue auguste renoir | H9: 400

Sheet contrat
Q3: Contrat de Location de Matériel Event Dreams
AO53: Rendre les meilleurs moments plus spéciaux
B59: Contrat de location
E64: Le présent contrat de location de matériel est établi et conclu le | AY64: =INDIRECT("'information général'!E4") -> 45565 | BH64: entre Eventdream et
E65: =INDIRECT("'information général'!D4") | AD65: ; collectivement dénommées" les “parties”.
E66: Le propriétaire loue le matériel suivant au locataire, qui doit adhérer aux termes et conditions du présent
E67: contrat :
N69: ↳ Les Parties conviennent de ce qui suit :
H72: 1- MATÉRIEL.
D73: Description du matériel | AO73: Quantité | AW73: Prix unitaire | BH73: Sous-total | BR73: Prix unité endommagé
D75: =devis!B24 | AO75: =devis!E24 | AW75: =devis!F24 | BH75: =devis!G24 | BR75: =devis!N12
D76: =devis!B25 | AO76: =devis!E25 | AW76: =devis!F25 | BH76: =devis!G25 | BR76: =devis!N13
D77: =devis!B26 | AO77: =devis!E26 | AW77: =devis!F26 | BH77: =devis!G26 | BR77: =devis!N14
D78: =devis!B27 | AO78: =devis!E27 | AW78: =devis!F27 | BH78: =devis!G27 | BR78: =devis!N15
D79: =devis!B28 | AO79: =devis!E28 | AW79: =devis!F28 | BH79: =devis!G28 | BR79: =devis!N16
D80: =devis!B29 | AO80: =devis!E29 | AW80: =devis!F29 | BH80: =devis!G29 | BR80: =devis!N17
D81: =devis!B30 | AO81: =devis!E30 | AW81: =devis!F30 | BH81: =devis!G30 | BR81: =devis!N19
D82: =devis!B31 | AO82: =devis!E31 | AW82: =devis!F31 | BH82: =devis!G31 | BR82: =devis!N21
D83: =devis!B32 | AO83: =devis!E32 | AW83: =devis!F32 | BH83: =devis!G32 | BR83: =devis!N22
D84: =devis!B33 | AO84: =devis!E33 | AW84: =devis!F33 | BH84: =devis!G33 | BR84: =devis!N23
D85: =devis!B34 | AO85: =devis!E34 | AW85: =devis!F34 | BH85: =devis!G34 | BR85: =devis!N24
D86: =devis!B35 | AO86: =devis!E35 | AW86: =devis!F35 | BH86: =devis!G35 | BR86: =devis!N26
D87: =devis!B36 | AO87: =devis!E36 | AW87: =devis!F36 | BH87: =devis!G36 | BR87: =devis!N27
D88: =devis!B37 | AO88: =devis!E37 | AW88: =devis!F37 | BH88: =devis!G37 | BR88: =devis!N28
D89: TOTAL | AO89: =devis!F40 -> 0 | BR89: =devis!N29
H94: 2- DURÉE DE LA LOCATION.
E95: La période de location commencera le | AG95: =INDIRECT("'information général'!E4") -> 45565 | AQ95: et se terminera le | BD95: =INDIRECT("'information général'!F4") -> 45567
H98: 3- MONTANT DE LA LOCATION.
E99: Le locataire s'engage à payer le montant de | AK99: =AO89 -> 0 | AS99: au propriétaire en tant que loyer pour le matériel.
E100: En déduction de l’acompte déjà payé d'une valeur de | AR100: =INDIRECT("'information général'!J4") | AW100: Reste dû : | BF100: =INDIRECT("'information général'!I4") -> 0
H103: 4- FRAIS SUPPLÉMENTAIRES.
E104: Des frais supplémentaires seront ajoutés dans le cas où le matériel est endommagé ,
E105: manque des pièces, ou est retourné plus tard que la durée de location.
B113: Contrat de location
H123: 5- UTILISATION DU MATÉRIEL
E124: Le matériel doit être utilisé de manière prudente et appropriée. Son utilisation doit être
E125: conforme à toutes les lois et réglementations relatives à la possession, l'utilisation
E126: ou l'entretien du matériel.
H130: 6- DÉPÔT DE GARANTIE.
E131: En plus des frais de location, le locataire devra verser un dépôt de garantie de | BI131: =INDIRECT("'information général'!H4")
E132: avant de recevoir tout Matériel et au moment de la signature du présent contrat
E133: Ce dépôt sera restitué au locataire à la fin du présent contrat lors de la restitution du
E134: matériel déduction faite des éventuels dommages.
H137: 7- TRANSPORT.
E139: Le locataire | N139: FALSE | P139: est ou | U139: FALSE | W139: n’est pas responsable pour l’ensemble des frais et coûts.
E140: Au début de la période de location, Au début de la période de location
E141: à l’adresse suivante : | U141: =INDIRECT("'information général'!G4")
E142: Et à la fin de la période de location, pour la livraison du matériel de l’adresse ci-dessus aux
E143: locaux du propriétaire.
H146: 8- ÉTAT DU MATÉRIEL
E148: Le locataire ou son représentant a inspecté le matériel énuméré dans la section 1 et
E149: reconnaît qu'il est en bon état de fonctionnement.
H152: 9- RESPONSABILITÉS ET ENTRETIEN DU MATÉRIEL.
E154: Le locataire s'engage à maintenir le matériel propre et en bon état de fonctionnement
E155: pendant la durée de la location, à ses propres frais. En cas de perte ou d'endommagement
E156: irréparable du matériel, le locataire devra payer au propriétaire le coût de remplacement
E157: du matériel précisé sur le tableau en annexe du présent contrat .
H159: 10- PROPRIÉTÉ.
E161: Le matériel est et restera la propriété exclusive du propriétaire.
B169: Contrat de location
H177: 11-INDEMNISATION.
E179: À l'exception des dommages, réclamations ou pertes dus aux actes ou à la négligence du
E180: propriétaire, le locataire, dans la mesure permise par la loi, indemnisera et tiendra le
E181: propriétaire et les biens du propriétaire, libres et exonérés de toute responsabilité pour les
E182: pertes, réclamations, blessures ou décès de toute personne, y compris le locataire, ou pour
E183: les dommages aux biens découlant de l'utilisation et de la possession du matériel par
E184: le locataire ou des actes ou omissions de toute personne, y compris le locataire, utilisant
E185: ou possédant l'équipement avec le consentement exprès ou implicite du locataire.
H187: 12-INTÉGRALITÉ DU CONTRAT.
E189: Le présent contrat constitue l'intégralité de l'accord entre les parties et remplace toute
E190: entente ou représentation antérieure de quelque nature que ce soit avant la date du
E191: présent contrat. Il n'existe aucune autre promesse, condition, entente ou autre accord,
E192: oral ou écrit, relatif à l'objet du présent contrat. Le présent contrat peut être
E193: modifié par écrit et doit être signé par le propriétaire et le locataire
E198: En FOI DE QUOI, les parties ont fait signer le présent contrat le jour et l'année indiqués
E199: ci-dessus.
E205: EVENTDREAM:
E210: LE LOCATAIRE

Sheet facture

Sheet liste de matériel
A1: matériel | B1: prix de location | C1: prix d'achat
A2: table ronde | B2: 11 | C2: 70
A3: table rectangulaire | B3: 11 | C3: 50
A4: fourchette | B4: 0.3 | C4: 0.5
A5: petite cuillères | B5: 0.75 | C5: 0.5
A6: grande cuillére | B6: 0.75
A7: petite ascette V1 | B7: 0.75
A8: grande ascette V1 | B8: 0.75
A9: petite asciette préstige | B9: 1
A10: grande asciette préstige | B10: 1
A11: chaise nappoléon | B11: 3
A12: chaise pliante noir | B12: 1.75
A13: hausse de chaise | B13: 1
A14: nappe rond blanche | B14: 8
A15: nappe réctangulaire | B15: 8
A16: livraison au pied de camion

Sheet commandes
A5: Cofirmé ou pas ? | B5: N° de devis | C5: Date de sortie | D5: Date de retour | E5: Matériel loué | F5: total mensuel | G5: livraison | H5: montant total | I5: Acompte payé | J5: reste à payer | K5: adresse de livraison | L5: Moyen de contact | M5: Nom | N5: Mtt du chèque | O5: Heure du retrait
A6: documents | B6: nadia | C6: 44755 | D6: 44757 | E6: 3 tables 30 chaises | H6: 68 | I6: 0 | J6: 68
A7: FATAH | B7: fatah | C7: 44820 | D7: 44822 | E7: 2 table 2 nappe | H7: 32 | I7: 0 | J7: 32
A8: BAYA | B8: baya | C8: 44820 | D8: 44822 | E8: 100 kit vaisselle 10 tables 10 nappes mange debeou nappe | H8: 240 | I8: 0 | J8: 240
B9: RETIBALLAH | C9: 44841 | D9: 44843 | E9: 2 table 2 nappes | F9: =SUM(H9:H14) -> 584 | G9: 36 | H9: 68 | I9: 0 | J9: 68
B10: AWA | C10: 44847 | D10: 44849 | E10: 140 verres | F10: =SUM(H15:H18) -> 279 | H10: 84 | I10: 0 | J10: 84
B11: stephanie | C11: 44848 | D11: 44850 | E11: 12 table | H11: 96 | I11: 0 | J11: 96
C12: 44848 | D12: 44850 | E12: 30 cHAISE | H12: 30 | I12: 0 | J12: 30
B13: julie | C13: 44856 | D13: 44859 | E13: 136 kit vaisselle /S | H13: 170 | I13: 60 | J13: 110
B14: norah | C14: 44856 | D14: 44859 | E14: 7 tables ronde | G14: 80 | H14: 136 | I14: 34.61 | J14: 0
B15: AYMEN | C15: 44863 | D15: 44866 | E15: 25 kits | H15: 25 | I15: 0 | J15: 25
C16: 44876 | D16: 44878 | E16: 120 KIT/S | H16: 150 | I16: 50 | J16: 100
B17: PINDA | C17: 44876 | D17: 44878 | E17: 3 TABLES | H17: 24 | I17: 0 | J17: 24
B18: NAIMA | C18: 44892 | D18: 44894 | E18: 80 KITS | H18: 80 | I18: 0 | J18: 80
A19: LEILA | B19: LEILA | C19: 44897 | D19: 44899 | E19: 5 tables 5 NAPPES RONDE 4 NAPPE RECT LIV | F19: =SUM(H19:H20) -> 215 | G19: 38 | H19: 150 | I19: 50
A20: jsp | B20: HOUSSE | C20: 44905 | D20: 44905 | E20: 40 housse | G20: 33 | H20: 65 | I20: 0 | J20: 65
B21: Amina sidhoum | C21: 44944 | D21: 44946 | E21: 80 kits | F21: =SUM(H21:Z24) -> 640 | H21: 80 | I21: 0 | J21: 80
B22: CHAISE | C22: 44953 | D22: 44946 | E22: 2tables rectan 20 kits 20 housse | G22: 28 | H22: 80 | I22: 0 | J22: 80
A23: jsp | B23: TABLE | C23: 44953 | D23: 44955 | E23: 8 Tables | G23: 16 | H23: 80 | I23: 0 | J23: 80
A24: sidhoum | C24: 44953 | D24: 44955 | E24: 40 chaises | G24: 40 | H24: 80 | I24: 25 | J24: 55
A25: JSP | C25: 44960 | D25: 44962 | E25: 35 chaises 1 table rect | F25: =SUM(H25:H34) -> 636.96 | G25: 29.98 | H25: 74.98 | I25: 0 | J25: 75
A26: JSP | B26: CHAISE | C26: 44961 | D26: 44963 | E26: 35 CHAISE LIV 1 TABLE RECT | G26: =65-35-8 -> 22 | H26: 64.98 | I26: 0 | J26: 65
A27: benzid sonia | C27: 44968 | D27: 44970 | E27: 80 kits | H27: 80 | I27: 25 | J27: 55
A28: jsp | C28: 44969 | D28: 44971 | E28: 12 chaises | H28: 0
A29: bensalem | C29: 44974 | D29: 44975 | E29: 4 tables et 4 nappes rondes | H29: 72 | I29: 27 | J29: 45 | K29: NON | L29: WTHSAP (4tables et 4 nappes) | M29: Myriam Bensalem | N29: 200 | O29: 14H30
A30: JSPg | C30: 44974 | D30: 44976 | E30: 30 chaises | G30: 39.99 | H30: 69.98€ | I30: 24.98€ | J30: 45 | K30: Paris 12 | L30: Leboncoin(dembele) | M30: Bintou Dembele | N30: 100
A31: JSP | C31: 44974 | D31: 44977 | E31: 3O chaises | G31: 39.99 | H31: 69.98€ | I31: 24.98€ | J31: 45 | K31: Massy Palaiseau | L31: Assos 30 chaises (wtsp) | M31: Baptiste Copin | N31: 100
A32: JSP | C32: 44975 | D32: 44975 | E32: 8 tables | G32: 30 | H32: 140 | I32: 0 | J32: 140 | K32: Champigny | L32: Urgent | N32: 400
A33: BOUDFOUSS | C33: 44978 | D33: 44979 | E33: 25 Chaises | H33: 25 | I33: 0 | J33: 25 | K33: NON | L33: Naissance Omra | N33: 100 | O33: 12h00
A34: halimata | B34: via msg 15 FEV | C34: 44981 | D34: 44982 | E34: 200 kits ( assiette cuilliere verre ) | H34: 180 | I34: 180 | J34: 0 | L34: 150 kits sevran
A35: contrat Ingrid.pdf | B35: 23_02_2023_IngridK | C35: 44988 | D35: 44989 | E35: 100 Kit propre | F35: =SUM(H35:H40) -> 283.8 | H35: 100 | I35: 30 | J35: 70 | K35: NON | L35: INGRIDK(leboncoin) | N35: 250
A36: JSP | B36: Devis_24_02_2023 | C36: 44988 | D36: 44989 | E36: 35 Chaises | G36: 25 | H36: 85 | I36: 25 | J36: 60 | K36: Rosny-sous-Bois | L36: Ams 35 Chaises | M36: Adjinaya Fatoumata | N36: 200 | O36: 16h30 et retrait à 18h00 | P36: 5 Rue de lisbonne 93 110 Rosny-sous-bois
B37: Devis_06_03_2023 | C37: 44993 | D37: 44998 | E37: 70 chaises et 50 housses | G37: 39.98 | H37: 259.98€ | I37: 84.98€ | J37: 175 | K37: Paris 12 | L37: Mme Connet | M37: Fatoumata Kone | N37: 500
A38: jsp | C38: 45002 | D38: 45003 | E38: 50 chaises | H38: 50 | I38: 15 | J38: 35 | K38: NON | L38: Leboncoin(Z.ROD) | M38: Rodolphe Zadi | N38: 100
A39: pearl caffa | B39: Devis_11_03_2023 | C39: 45002 | D39: 45004 | E39: 20 Chaises +2 housse +livraison à Paris 13 | G39: 38.38 | H39: 59.98€ | I39: 0 | J39: 59.98 | K39: Paris 13 | L39: Leboncoin(Pearlychouw)
A40: JSP | C40: 45003 | D40: 45005 | E40: 11 chaises 11 housse 1 nappe table 11 kit vaisselle | H40: 48.8 | I40: 18.8 | J40: 30
A41: JSP | C41: 45024 | D41: 45026 | E41: 30 CHAISE | F41: =SUM(H41:H45) -> 473 | H41: 30 | I41: 0 | J41: 30
A42: jsp | C42: 45036 | D42: 45038 | E42: 20 chaises | H42: 20 | I42: 0 | J42: 20
A43: contrat de location ismahane.pdf | B43: 26_02_2023_Sarah | C43: 45037 | D43: 45038 | E43: 6 tables rondes chaises housse nappes centre | G43: 39 | H43: 323 | I43: 113 | J43: 210 | K43: Villejuif | L43: Leboncoin (Sarah) | M43: Ismahane el Mir | N43: 450 | P43: 5 Allée Sonia delaunay, villejuif
A44: contrat leslie.pdf | B44: Pas de devis | C44: 45044 | D44: 45046 | E44: 30 Chaise | H44: 30 | I44: 30 | J44: 0 | K44: NON | L44: Leboncoin (Leslie) | M44: Leslie Noundou | N44: 150 | O44: Samedi à 11H00
A45: contrat Ornella.pdf | B45: devis_29_04_2023 | C45: 45045 | D45: 45046 | E45: 4 tables rondes et 30 chaises pliantes | H45: 70 | I45: 25 | J45: 45 | K45: NON | L45: Wtsp (Persan) | N45: 450 | O45: Samedi à 12H00
A46: contrat Wiam.pdf | B46: devis 07_04_23 | C46: 45046 | D46: 45048 | E46: 75 kits propre 75 housses 8 nappes rondes 3 napes rectan 8 centre de tables | F46: =SUM(H46:H63) -> 2043.98 | H46: 279 | I46: 99 | J46: 180 | L46: wthsp (catalogue) | M46: Wiam Benchabane | N46: 250 | O46: Dimanche à 10h00
A47: JSP | B47: devis _01_10_23 | C47: 45051 | D47: 45052 | E47: 300 Kits rendu sale | H47: 375 | I47: 125 | J47: 250 | K47: NON (mais possible à ivry à 25€ * 2 | L47: L'ancien compte leboncoin + msg (300 kits 6 Mai | M47: Dioums
A48: stefi | C48: 45052 | D48: 45054 | E48: 25 chaises 20 housses | H48: 25 | I48: 10 | J48: 15 | K48: NON | L48: Leboncoin (Caprisun) | M48: The Womens dates | N48: 150 | O48: 16H00 | P48: NON
A49: jsp | C49: 45052 | D49: 45054 | E49: 60 chaises | H49: 60 | I49: 0 | J49: 60
A50: jsp | B50: Devis_22_03_2023 | C50: 45058 | D50: 45060 | E50: 25 Chaises | G50: =66-25 -> 41 | H50: 65.98€ | I50: 25.98€ | J50: 40 | K50: Cachan | L50: Leboncoin (Reginah) | M50: Regina Yarabou | N50: 150 | P50: 17 Avenue de l'europe 94230 Cachan, 0758721090
A51: BENDA | C51: 45058 | D51: 45060 | E51: 40 Housses | H51: 32 | I51: 0 | J51: 0
A52: naoumi | C52: 45059 | D52: 45060 | E52: 60 kits sale 5 tables 5nappes 5centre de table | G52: 50 | H52: 265 | I52: 85 | J52: =265-85 -> 180 | K52: Cachan | L52: Leboncoin (Naomie28) | M52: Naomie MBALA IFONDA | N52: 400 | O52: Entre 8h et 10h | P52: Adresse à demander
A53: ZERROKI NADIA | C53: 45059 | D53: 45060 | E53: 6 chaises | H53: 6 | I53: 0 | J53: 0
A54: sarah | C54: 45059 | D54: 45060 | E54: 50 chaises | G54: 50 | H54: 100 | I54: 0 | J54: 0 | K54: Alfortville | L54: 73 chaises alfortville | M54: Sarah | N54: 350
A55: contrat de location Séverine.pdf | B55: Devi sev | C55: 45065 | D55: 45067 | E55: 2 table nappe kits chaises housses | H55: 92 | I55: 32 | J55: 60
A56: Contrat location zahiyali.pdf | B56: Devis 01/04/2023 | C56: 45065 | D56: 45067 | E56: 200kits | H56: 200 | I56: 100 | J56: 100 | K56: NON | L56: Leboncoin (Zayihali) | N56: 250 (A revoir avec la cliente car elle loue beaucoup moins que prévu)
A57: jsp | C57: 45065 | D57: 45067 | E57: 20 chaises | H57: 20 | I57: 0 | J57: 20
A58: jsp | C58: 45066 | D58: 45068 | E58: 40 chaises pliante | G58: 49.98 | H58: 89.98 | I58: 0 | J58: 90
A59: KONTI | B59: Pas de devis | C59: 45070 | D59: 45072 | E59: 40 chaises | G59: 40 | H59: 80 | I59: 30 | J59: 50 | K59: Paris 12 | L59: 50 chaises Paris 12 | M59: Assa Konte | N59: 300 | O59: A partir de 16h00 | P59: 2 rue Henri Desgrange 75012
A60: EHOULAN | B60: 18/02/2023_50_convives | C60: 45072 | D60: 45073 | E60: 5 table ronde 5nappe 50 housse 40 Chaises 1 mange debout + nappe | G60: 40 | H60: 183 | I60: 63 | J60: =183-63 -> 120 | L60: 50 A 60 convives cachan
B61: Pas de devis | C61: 45072 | D61: 45073 | E61: 5 tables rectangulaire | G61: 50 | H61: 99.98€ | I61: 0 | J61: 99.98€ | K61: Alforville | L61: 73 chaises alfortville | M61: Sarah
A62: contrat de location Nacima.pdf | B62: Devis_09_03_2023 | C62: 45072 | D62: 45074 | E62: 11 centre de table 100 kit propre | H62: 177 | I62: 77 | J62: 100 | L62: Wthsp (26 Mai Centre de Table et 100 Kits) | M62: Nacima Mimi | N62: 400
A63: jsp | B63: Pas de devis | C63: 45072 | D63: 45074 | E63: 30 Housses + 36 chaises | H63: 60 | I63: 0 | J63: 60
A64: TRAOUR2 | C64: 45080 | D64: 45082 | E64: 10 Centres de table | F64: =SUM(H64:H71) -> 674.6 | H64: 70 | I64: 40 | J64: 30 | K64: NON | L64: Leboncoin (mariame.Tr | M64: Mariame Traore | N64: 150
A65: JSP | B65: Devis_18_05_2023 | C65: 45086 | D65: 45088 | E65: 6 tables rectangulaires +Nappes +50 chaises + housses + 50 kits | H65: 249 | I65: 100 | J65: 149 | K65: Creteil | L65: wthsp (Creteil 50 chaises housses table) | M65: Cynthiche gnahoua | N65: 550
A66: noure | B66: NOURE | C66: 45086 | D66: 45088 | E66: 45 kits 30 chaises 3 tables 3 nappes | H66: 0 | I66: 0 | J66: 0
A67: JSP | B67: Devis 31_03_2023 | C67: 45093 | D67: 45095 | E67: 32 kits 32 chaises 32 Housse de chaise 4 tables rectangulaire 4 nappes rectangulaire 4 mange 4nappes mange debout | H67: 233.6 | I67: 74 | J67: 160 | L67: Leboncoin (info photos) | M67: Laure Gbolou
B68: Pas de devis | C68: 45093 | D68: 45095 | E68: 40 housse | H68: 32 | I68: 10 | J68: 22 | K68: NON | L68: Leboncoin (Ophélie94600) | M68: Ophélie Lemaire
C69: 45093 | D69: 45095 | E69: 10 chaises | H69: 10 | I69: 0 | J69: 10
B70: pas de devis | C70: 45100 | D70: 45102 | E70: 40 CHAISES | H70: 40 | I70: 15 | J70: 25 | K70: NON | L70: LEBONCOIN | M70: MORGAN | N70: 250
B71: pas de devis | C71: 45100 | D71: 45102 | E71: 40 CHAISES | H71: 40 | I71: 0 | J71: 40
B72: Pas de devis | C72: 45113 | D72: 45115 | E72: 4 Tables rondes | F72: =SUM(H72:H75) -> 171 | H72: 40 | I72: 10 | J72: 30 | K72: NON | L72: LEBONCOIN (Events) | M72: Kmb events | N72: 350
C73: 45121 | D73: 45123 | E73: 350 assiettes sales + 20 couteaux | H73: 111 | I73: 180 | J73: A rendre 69€ | K73: NON | L73: wthsp (150 Assiettes sales 150- 45) | M73: Adrienne Guerevicko | N73: 350
C74: 45121 | D74: 45123 | E74: 4 nappes + 2 tables | H74: 20 | I74: 0 | J74: 20 | K74: non
B75: Pas de devis | C75: 45177 | D75: 45179 | E75: 17 kits à rendre sale + 17 bols + 17 verres | H75: 44.20€ | I75: 14.20€ | J75: 30 | K75: NON | L75: Wtsp (Vaiselle 9 Septembre) | M75: Jason NIJEAN | N75: 50
A76: Pas de devis | C76: 45177 | D76: 45179 | E76: 7 mange debout et 7 housse | F76: =SUM(H76:H80) -> 807 | H76: 98 | I76: 35 | J76: 63 | L76: Leboncoin | M76: safaa | N76: 250
A77: devis 28/08/23 | C77: 45178 | D77: 45181 | E77: 80 chaises 10 tables livraison | G77: 40 | H77: 280 | I77: 80 | J77: 200 | K77: kremlin bicetre | L77: telephone | M77: lise kadoum | N77: 400 | P77: 10 rue danton kremlin bicetre
A78: Devis 01/09/23 | C78: 45191 | D78: 45193 | E78: 4 tables 40 chaises 4 Nappes rectangulaires | G78: 20 | H78: 180 | I78: 44 | J78: 136 | K78: Chevillylarue | L78: Leboncoin | M78: Flore | N78: 300 | P78: 4 rue d'anjou , chevilly-larue | R78: 8DN82440K04459609
A79: devis_23_09_23 | B79: devis_23_09_23 | C79: 45191 | D79: 45193 | E79: 12 nappes rondes + 120 housses de chaise | H79: 210 | I79: 70 | J79: 140 | K79: non | L79: telephone (12 nappes et 120 housses) | M79: ISSA Aya | N79: 250
A80: Devis_23_11_23 | B80: Devis_23_11_23 | C80: 45192 | D80: 45194 | E80: 2 table rectangulaire + 10 chaises | H80: 39 | I80: 27 | J80: 12 | K80: non | L80: telephone ( 23 novembre) | M80: Mohamed BOUAGACHE | N80: 150
A81: Devis_30_09_2023 | B81: Devis_30_09_2024 | C81: 45198 | D81: 45200 | E81: 49 Kits vaisselle rendus sales | F81: =SUM(H81:H83) -> 98 | H81: 98 | I81: 38 | J81: 60 | K81: non | L81: telephone (eragny) | M81: Elsa AIT BELKACEM | N81: 200
A82: Devis_30_09_2024 | B82: Devis_30_09_2025 | C82: 45198 | D82: 45200 | E82: 50 housses de chaise | G82: 20 | H82: 72.50€ | I82: 22.50€ | J82: 50 | K82: Villejust | L82: telephone (Alexandra granger villejust | M82: Alexandra lakhdar granger | N82: 250 | P82: Parc des 2 lacs villejust 91140
A83: Devis_30_09_23 | B83: Devis_30_09_23 | C83: 45198 | D83: 45200 | E83: 35 kits vaisselle rendus sales + 35 Housses de chaise + 4 nappes rectang + 4 centre table + 4 tables rectangulaires | G83: 57.5 | H83: 271.75€ | I83: 75.25€ | J83: 196.50€ | K83: Clamart | L83: telephone (catalogue) | M83: Wiam Benchabane + Karim Ben taieb | N83: 450 | P83: 24 Rue de bretagne 92140 Clamart
A84: Devis_05_11_23 | C84: 45235 | D84: 45236 | E84: 1 Table ronde, 1 Mange debout 10 chaises | F84: =SUM(H84:H86) -> 77 | G84: 40 | H84: 77 | I84: 27 | J84: 50 | K84: Thiais | L84: Leboncoin (Morgan.P) | M84: Morgane Pinas | N84: 200 | O84: 12h00 | P84: 45 Avenue du Président Franklin Roosvelt, 94320 Thiais
A85: Devis_18_11_23 | C85: 45247 | D85: 45249 | E85: 1 Table et 15 chaises | H85: 34.50€ | I85: 14.50€ | J85: 20 | K85: NON | L85: Wtsp (Cousine) | M85: Fatiha jeffali | N85: 250
A86: Nourelhouda | C86: 45247 | D86: 45249
C87: 45269 | D87: 45271 | E87: Table 2 nappe 20 chaises 20 housses | F87: 77 | H87: 77 | I87: 0 | J87: 77
C88: 45311 | D88: 45313 | E88: 50 chaises | F88: =SUM(H88:H89) -> 285 | G88: 40 | H88: 100 | I88: 35 | J88: 65 | K88: Kremlin Bicêtre
C89: 45317 | D89: 45319 | E89: 6 Centres de table tr , 1 table rect , 1 nappe rect , 1 panneau bvn | G89: 80 | H89: 185 | I89: 47 | J89: 138 | K89: Paris 18 | L89: Whatsapp | N89: 200 | P89: 143 rue de Clignancourt Paris 18
C90: 45347 | D90: 45347 | E90: 10 chaises | F90: 43 | G90: 30 | H90: 42.5 | I90: 12.5 | J90: 30 | K90: Kremlin Bicetre | N90: 50
C91: 45358 | D91: 45360 | E91: 60 Chaises | F91: 125 | H91: 125 | I91: 45 | J91: 80 | K91: Paris 15 | L91: Leboncoin + wathsap | M91: Zoheir Younes | N91: 300 | O91: 18h | P91: 24 rue d'alleray 75015 Paris
C92: 45388 | D92: 45388 | E92: 50 Chaises | F92: =SUM(H92:H97) -> 595.75 | H92: 102.50€ | I92: 32.50 | J92: 70 | K92: Gentilly | L92: Leboncoin (Rachedi)+ wthsapp | M92: KRB productions | N92: 150 | O92: Entre 9h et 11h et retour à 20h | P92: 89-93 Av. Paul Vaillant Couturier , Gentilly 94250
C93: 45393 | D93: 45394 | E93: 60 chaises | G93: 50 | H93: 125 | I93: 45 | J93: 80 | K93: Paris 15 | L93: Z machine
C94: 45401 | D94: 45403 | E94: 1 table rect 30 chaises | H94: 47.5 | I94: 17.5 | J94: 30 | M94: Sabrina ngami | N94: 150 | O94: Vendredi soir
C95: 45402 | D95: 45403 | E95: 25chaises 2 tables | H95: 51.25 | I95: 20 | J95: 31.25 | M95: Fatim touré
C96: 45406 | D96: 45408 | E96: 120 kits vaisselle | G96: 38 | H96: =240+76 -> 316 | I96: 116 | J96: 200 | K96: Bobigny | L96: Wathsapp (Inès Kindi) | M96: Inès Kindi | N96: 300 | O96: A voir avec le client | P96: 70 Rue Henri Barbusse, Bobigny | R96: On lui a fait la vaisslle à l'ancien prix 2€
C97: 45407 | D97: 45409 | E97: 32 Kits vaisselle rendu sale | H97: 56 | I97: 16 | J97: 40 | L97: Wathsapp (Inès Kindi) | M97: Inès Kindi | N97: 100
C98: 45417 | D98: 45418 | E98: 10tables | F98: =SUM(H98:H106) -> 661.47 | G98: 80 | H98: 190 | I98: 0 | J98: 190 | K98: Z machine
C99: 45419 | D99: 45421 | E99: 7 nappes | H99: 56 | I99: 0 | J99: 56 | L99: Sœur de Dalila teyaba
C100: 45422 | D100: 45424 | E100: 2 tables rondes | H100: 20 | I100: 0 | J100: 20
C101: 45422 | D101: 45424 | E101: 3tables rondes 30 chaises 3 nappes | G101: 60 | H101: =154 -> 154 | I101: 50 | J101: =104 -> 104 | L101: Wathapp tandart
C102: 45430 | D102: 45431 | E102: 50 chaises | H102: 62.5 | I102: 0 | J102: 62.5 | L102: Leboncoin nihasina
C103: 45430 | D103: 45431 | E103: 1table 10 housses 10chaises 1 nappes | H103: 40.5 | I103: 0 | J103: 40.5 | K103: Appel
C104: 45430 | D104: 45432 | E104: 2 table rondes | H104: 20 | I104: 10 | J104: 10 | L104: Whatapp 0769689698 | N104: 200
...
